somax/__init__.py
somax/diagonal/__init__.py
somax/diagonal/adahessian.py
somax/diagonal/sophia_g.py
somax/diagonal/sophia_h.py
somax/gn/__init__.py
somax/gn/egn.py
somax/gn/sgn.py
somax/hf/__init__.py
somax/hf/newton_cg.py
somax/ng/__init__.py
somax/ng/swm_ng.py
somax/qn/__init__.py
somax/qn/sqn.py
python_somax-0.0.1.dist-info/LICENSE
python_somax-0.0.1.dist-info/METADATA
python_somax-0.0.1.dist-info/WHEEL
python_somax-0.0.1.dist-info/top_level.txt
python_somax-0.0.1.dist-info/RECORD
